calcpkg-2.0.1.dist-info/top_level.txt
calcpkg-2.0.1.dist-info/DESCRIPTION.rst
calcpkg-2.0.1.dist-info/metadata.json
calcpkg-2.0.1.dist-info/METADATA
calcpkg-2.0.1.dist-info/entry_points.txt
calcpkg-2.0.1.dist-info/RECORD
calcpkg-2.0.1.dist-info/WHEEL
calcrepo/info.py
calcrepo/calcpkg.py
calcrepo/__init__.py
calcrepo/output.py
calcrepo/repo.py
calcrepo/index.py
calcrepo/util.py
calcrepo/repos/__init__.py
calcrepo/repos/cemetech.py
calcrepo/repos/ticalc.py
calcrepo/repos/omnimaga.py
