Metadata-Version: 2.0
Name: calcpkg
Version: 2.0.1
Summary: ticalc.org package manager
Home-page: https://github.com/TC01/calcpkg
Author: Ben Rosser
Author-email: rosser.bjr@gmail.com
License: MIT
Keywords: ticalc calculator packages
Platform: UNKNOWN
Classifier: Development Status :: 5 - Production/Stable
Classifier: Intended Audience :: Developers
Classifier: Intended Audience :: End Users/Desktop
Classifier: Topic :: Software Development :: Libraries
Classifier: Topic :: Internet :: WWW/HTTP :: Indexing/Search
Classifier: Topic :: Internet :: WWW/HTTP :: Dynamic Content
Classifier: License :: OSI Approved :: MIT License
Classifier: Programming Language :: Python :: 2
Classifier: Programming Language :: Python :: 2.7
